dataset_builder/__init__.py
dataset_builder/analysis/__init__.py
dataset_builder/analysis/analyzer.py
dataset_builder/analysis/cross_reference.py
dataset_builder/analysis/matching.py
dataset_builder/analysis/scanner.py
dataset_builder/builder/__init__.py
dataset_builder/builder/copier.py
dataset_builder/builder/copy_matched_species.py
dataset_builder/builder/io.py
dataset_builder/builder/walker.py
dataset_builder/builder/web_crawl/__init__.py
dataset_builder/builder/web_crawl/fetcher.py
dataset_builder/builder/web_crawl/parser.py
dataset_builder/builder/web_crawl/scraper.py
dataset_builder/builder/web_crawl/web_crawler.py
dataset_builder/core/__init__.py
dataset_builder/core/constants.py
dataset_builder/core/exceptions.py
dataset_builder/core/log.py
dataset_builder/core/utility.py
dataset_builder/core/config/__init__.py
dataset_builder/core/config/interactive_builder.py
dataset_builder/core/config/loader.py
dataset_builder/core/config/schema.py
dataset_builder/core/config/validator.py
dataset_builder/deprecated/other_dataset_builder.py
dataset_builder/deprecated/train_val_splitter.py
dataset_builder/manifest/__init__.py
dataset_builder/manifest/composition.py
dataset_builder/manifest/data_preparer.py
dataset_builder/manifest/exporter.py
dataset_builder/manifest/identifying_dominant_species.py
dataset_builder/manifest/manifest_builder.py
dataset_builder/visualization/__init__.py
dataset_builder/visualization/visualizer.py
dataset_builder_inat-1.0.8.dist-info/METADATA
dataset_builder_inat-1.0.8.dist-info/WHEEL
dataset_builder_inat-1.0.8.dist-info/top_level.txt
dataset_builder_inat-1.0.8.dist-info/RECORD
