Metadata-Version: 2.4
Name: dataset_builder_inat
Version: 1.0.8
Summary: A modular Python toolkit for building, analyzing, and visualizing fine-grained classification datasets from iNaturalist. Includes tools for web crawling, species filtering, class balancing, and manifest generation.
Author-email: HoangPham4171 <hoangpham4171@gmail.com>
License-Expression: MIT
Project-URL: Homepage, https://github.com/HoangPham6337/iNaturelist_dataset_builder
Project-URL: Repository, https://github.com/HoangPham6337/iNaturelist_dataset_builder
Requires-Python: >=3.11
Requires-Dist: bs4>=0.0.2
Requires-Dist: pandas>=1.1.5
Requires-Dist: pyarrow>=6.0.1
Requires-Dist: matplotlib>=3.3.4
Requires-Dist: matplotlib-venn>=1.1.2
Requires-Dist: numpy>=1.19.5
Requires-Dist: pandas>=1.1.5
Requires-Dist: pyyaml>=6.0.1
Requires-Dist: requests>=2.27.1
Requires-Dist: scikit-learn>=0.24.2
Requires-Dist: tqdm
